ln_aws_cdk_construct/_jsii/__init__.py
ln_aws_cdk_construct/_jsii/ln.aws.cdk.construct@0.0.0.jsii.tgz
ln_aws_cdk_construct-0.0.0.dist-info/LICENSE
ln_aws_cdk_construct-0.0.0.dist-info/METADATA
ln_aws_cdk_construct-0.0.0.dist-info/WHEEL
ln_aws_cdk_construct-0.0.0.dist-info/top_level.txt
ln_aws_cdk_construct-0.0.0.dist-info/RECORD
