Metadata-Version: 2.1
Name: ln-aws-cdk-construct
Version: 0.0.0
Summary: ln.aws.cdk.construct
Home-page: https://github.com/github-lernender-corp/ln.aws.cdk.construct
Author: Shawn Lovelidge<github@lernendercorp.com>
License: Apache-2.0
Project-URL: Source, https://github.com/github-lernender-corp/ln.aws.cdk.construct
Classifier: Intended Audience :: Developers
Classifier: Operating System :: OS Independent
Classifier: Programming Language :: JavaScript
Classifier: Programming Language :: Python :: 3 :: Only
Classifier: Programming Language :: Python :: 3.8
Classifier: Programming Language :: Python :: 3.9
Classifier: Programming Language :: Python :: 3.10
Classifier: Programming Language :: Python :: 3.11
Classifier: Typing :: Typed
Classifier: Development Status :: 5 - Production/Stable
Classifier: License :: OSI Approved
Requires-Python: ~=3.8
License-File: LICENSE
Requires-Dist: aws-cdk-lib<3.0.0,>=2.1.0
Requires-Dist: constructs<11.0.0,>=10.0.5
Requires-Dist: jsii<2.0.0,>=1.103.1
Requires-Dist: publication>=0.0.3
Requires-Dist: typeguard<5.0.0,>=2.13.3
